secop_cli/__init__.py
secop_cli/__main__.py
secop_cli/api.py
secop_cli/models/__init__.py
secop_cli/models/cli_models.py
secop_cli/models/mongo_models.py
secop_cli/transform.py
secop_cli-0.2.1.dist-info/METADATA
secop_cli-0.2.1.dist-info/WHEEL
secop_cli-0.2.1.dist-info/entry_points.txt
secop_cli-0.2.1.dist-info/RECORD
