Metadata-Version: 2.3
Name: secop-cli
Version: 0.2.1
Summary: Скриптовый интерфейс Secop
Author: Valeria Zaborovskaia, valeria.zaborovskaya@vkteam.ru
Requires-Python: >=3.11,<3.12
Classifier: Programming Language :: Python :: 3
Classifier: Programming Language :: Python :: 3.11
Requires-Dist: click (>=8.1.0,<8.2.0)
Requires-Dist: pydantic (>=2.9.0,<3)
Requires-Dist: pymongo (>=4.11.3,<5.0.0)
Requires-Dist: pytest (>=8.3.2,<9.0.0)
Requires-Dist: pyyaml (>=6,<7)
Requires-Dist: requests (>=2.22.0,<3.0.0)
Requires-Dist: responses (>=0.25.3,<0.26.0)
Requires-Dist: rich (>=13.0,<14.0)
Requires-Dist: shellingham (>=1.5,<2.0)
Requires-Dist: typer (>=0.12.3,<0.13.0)
